zoomfft2d/__init__.py
zoomfft2d/zoomfft2d.py
zoomfft2d-0.1.1.dist-info/METADATA
zoomfft2d-0.1.1.dist-info/WHEEL
zoomfft2d-0.1.1.dist-info/top_level.txt
zoomfft2d-0.1.1.dist-info/RECORD
