Metadata-Version: 2.4
Name: zoomfft2d
Version: 0.1.1
Summary: A Python package for performing zoomed 2D Fast Fourier Transforms using SciPy's ZoomFFT.
Author-email: "Sébastien M. Popoff" <sebastien.popoff@espci.fr>
License: CeCILL
Requires-Dist: numpy
Requires-Dist: scipy
Requires-Dist: matplotlib
